{"Battle":1,"Data":[{"HUD":[]},{"HUD":[{"Animations":[],"Children":[{"Animations":[{"ActivateType":{"RunType":1,"Type":0},"Duration":60,"EasingCurve":15,"EndOpacity":1,"Property":7,"Reset":true,"ReturnEasing":0,"StartOpacity":0,"Type":2}],"Conditions":[{"Code":"if (!$gameParty.inBattle() || BattleManager.actor() !== $gameParty.members()[0]) return false;\n    \nif (SceneManager._scene && SceneManager._scene._actorWindow && SceneManager._scene._actorWindow.active) return false;\n    \nreturn true;","Type":9}],"CustomProperties":{},"ID":301,"Name":"Whose turn is it?","Note":"","Opacity":1,"Rotation":0,"ShapeData":{"Color":"#ff0000","Height":238,"OutlineColor":"#000000","OutlineOpacity":100,"OutlineSize":2,"Shape":0,"Width":160},"Type":1,"X":7,"Y":117},{"Animations":[],"Children":[{"Animations":[],"Children":[],"CustomProperties":{},"ID":329,"Name":"Which ally?","Note":"","Opacity":1,"Rotation":0,"ShapeData":{"Color":"#00ff00","Height":238,"OutlineColor":"#000000","OutlineOpacity":100,"OutlineSize":2,"Shape":0,"Width":160},"Type":1,"X":-324,"Y":-180},{"Animations":[{"ActivateType":{"RunType":1,"Type":0},"Duration":60,"EasingCurve":12,"EndY":-25,"Property":1,"Reset":true,"ReturnEasing":0,"StartY":-40,"Type":2}],"CustomProperties":{},"ID":316,"Name":"Cursor Pointer","Note":"","Opacity":1,"PictureData":{"Picture":"finger_up"},"Rotation":0,"ScaleX":1.625,"ScaleY":1.625,"Type":2,"X":-323,"Y":-40}],"Conditions":[{"Code":"try {\n    if (!$gameParty.inBattle() || !SceneManager._scene || !SceneManager._scene._actorWindow) return false;\n    return SceneManager._scene._actorWindow.active && SceneManager._scene._actorWindow.index() === 0;\n} catch (e) {\n    return false;\n}","Type":9}],"CustomProperties":{},"Expanded":false,"GroupData":{},"ID":313,"Name":"Targeted as Ally","Note":"","Opacity":1,"Rotation":0,"Type":6,"X":331,"Y":298},{"Animations":[],"Children":[{"Animations":[],"CustomProperties":{},"ID":31,"Name":"OuContainer","Note":"","Opacity":1,"Rotation":0,"ShapeData":{"Color":"#ffffff","Height":156,"OutlineColor":"#000000","OutlineOpacity":100,"OutlineSize":2,"Shape":0,"Width":144},"Type":1,"X":7,"Y":15},{"Animations":[],"Children":[],"CustomProperties":{},"ID":45,"Name":"InContainer","Note":"","Opacity":1,"Rotation":0,"ShapeData":{"Color":"#ffffff","Height":130,"OutlineColor":"#000000","OutlineOpacity":100,"OutlineSize":2,"Shape":0,"Width":132},"Type":1,"X":7,"Y":17},{"Animations":[],"CustomProperties":{},"ID":359,"Name":"Actor Face","Note":"","Opacity":1,"PictureData":{"Code":"let actor = $gameParty.battleMembers()[0];\n\nlet aName = actor.name().replace(/\\\\[a-zA-Z]+\\[.*?\\]/g, '').replace(/[\\x00-\\x1F\\x7F-\\x9F]/g, '').trim().toLowerCase();\n\nlet stateStr = \"neutral\";\n\nif (actor.isDead()) {\n    stateStr = \"sleep\";\n} else if (actor.isStateAffected(3)) {\n    stateStr = \"heroic\";\n} else if (actor.isStateAffected(4)) {\n    stateStr = \"frantic\";\n} else if (actor.isStateAffected(5)) {\n    stateStr = \"hopeless\";\n} else if (actor.isStateAffected(6)) {\n    stateStr = \"martyr\";\n} else if (actor.isStateAffected(7)) {\n    stateStr = \"hysterical\";\n} else if (actor.isStateAffected(8)) {\n    stateStr = \"despair\";\n}\n\nreturn \"img/pictures/\" + aName + \"_\" + stateStr + \"_state.png\";","Picture":""},"Rotation":0,"ScaleX":0.5,"ScaleY":0.5,"Type":2,"X":7,"Y":16}],"CustomProperties":{},"Expanded":false,"GroupData":{},"ID":41,"Name":"Actor Card","Note":"","Opacity":1,"Rotation":0,"Type":6,"X":0,"Y":76},{"Animations":[],"Children":[{"Animations":[],"Children":[],"CustomProperties":{},"ID":360,"Name":"InContainer - Copy 2","Note":"","Opacity":1,"Rotation":0,"ShapeData":{"Color":"#ffffff","Height":32,"OutlineColor":"#000000","OutlineOpacity":100,"OutlineSize":2,"Shape":0,"Width":132},"Type":1,"X":88,"Y":162},{"Animations":[],"Conditions":[{"Code":"const actor = $gameParty.members()[0];\nif (!actor) return false;\n\nconst emotionStates = [3, 4, 5, 6, 7, 8]; \n\nreturn !emotionStates.some(id => actor.isStateAffected(id));","Type":9}],"CustomProperties":{},"ID":38,"Name":"Neutral Check","Note":"","Opacity":1,"Rotation":0,"ScaleX":0.627451,"ScaleY":0.833333,"TextData":{"Alignment":1,"Color":"#ffffff","FontFamily":"Gaegu-Bold.ttf","FontSize":32,"MaxWidth":200,"OutlineColor":"#000000","OutlineOpacity":100,"OutlineSize":7,"Text":{"Text":"NEUTRAL","Type":0}},"Type":0,"X":88,"Y":161},{"Animations":[],"Children":[{"Animations":[],"Children":[],"Conditions":[{"Code":"return $gameParty.members()[0] && $gameParty.members()[0].isStateAffected(3);","Type":9}],"CustomProperties":{},"ID":46,"Name":"Heroic Check","Note":"","Opacity":1,"Rotation":0,"ScaleX":0.627451,"ScaleY":0.833333,"TextData":{"Alignment":1,"Color":"#ffff00","FontFamily":"Gaegu-Bold.ttf","FontSize":32,"MaxWidth":200,"OutlineColor":"#000000","OutlineOpacity":100,"OutlineSize":4,"Text":{"Text":"HEROIC","Type":0}},"Type":0,"X":-324,"Y":-284},{"Animations":[],"Children":[],"Conditions":[{"Code":"return $gameParty.members()[0] && $gameParty.members()[0].isStateAffected(3);","Type":9}],"CustomProperties":{},"ID":281,"Name":"Heroic Turns - Copy 1","Note":"","Opacity":1,"Rotation":0,"ScaleX":0.5,"ScaleY":0.5,"TextData":{"Alignment":1,"Color":"#ffff00","FontFamily":"Gaegu-Bold.ttf","FontSize":32,"MaxWidth":200,"OutlineColor":"#000000","OutlineOpacity":100,"OutlineSize":4,"Text":{"Code":"var actor = $gameParty.members()[0]\nvar stateId = 3; \n\nif (actor && actor.isStateAffected(stateId)) {\n    return actor.stateTurns(stateId);\n} else {\n    return \"\";\n}","Display":"(code)","Type":7}},"Type":0,"X":-289,"Y":-291},{"Animations":[],"Children":[],"Conditions":[{"Code":"return $gameParty.members()[0] && $gameParty.members()[0].isStateAffected(4);","Type":9}],"CustomProperties":{},"ID":59,"Name":"Frantic Check","Note":"","Opacity":1,"Rotation":0,"ScaleX":0.627451,"ScaleY":0.833333,"TextData":{"Alignment":1,"Color":"#ff0000","FontFamily":"Gaegu-Bold.ttf","FontSize":32,"MaxWidth":200,"OutlineColor":"#000000","OutlineOpacity":100,"OutlineSize":4,"Text":{"Text":"FRANTIC","Type":0}},"Type":0,"X":-324,"Y":-284},{"Animations":[],"Children":[],"Conditions":[{"Code":"return $gameParty.members()[0] && $gameParty.members()[0].isStateAffected(5);","Type":9}],"CustomProperties":{},"ID":63,"Name":"Hopeless Check","Note":"","Opacity":1,"Rotation":0,"ScaleX":0.627451,"ScaleY":0.833333,"TextData":{"Alignment":1,"Color":"#0223ff","FontFamily":"Gaegu-Bold.ttf","FontSize":32,"MaxWidth":200,"OutlineColor":"#000000","OutlineOpacity":100,"OutlineSize":4,"Text":{"Text":"HOPELESS","Type":0}},"Type":0,"X":-324,"Y":-284},{"Animations":[],"Children":[],"Conditions":[{"Code":"return $gameParty.members()[0] && $gameParty.members()[0].isStateAffected(6);","Type":9}],"CustomProperties":{},"ID":68,"Name":"Martyr Check","Note":"","Opacity":1,"Rotation":0,"ScaleX":0.656863,"ScaleY":0.833333,"TextData":{"Alignment":1,"Color":"#a9ac00","FontFamily":"Gaegu-Bold.ttf","FontSize":32,"MaxWidth":200,"OutlineColor":"#000000","OutlineOpacity":100,"OutlineSize":4,"Text":{"Text":"MARTYR","Type":0}},"Type":0,"X":-324,"Y":-284},{"Animations":[],"Children":[],"Conditions":[{"Code":"return $gameParty.members()[0] && $gameParty.members()[0].isStateAffected(7);","Type":9}],"CustomProperties":{},"ID":69,"Name":"Hysterical Check","Note":"","Opacity":1,"Rotation":0,"ScaleX":0.627451,"ScaleY":0.833333,"TextData":{"Alignment":1,"Color":"#ff0000","FontFamily":"Gaegu-Bold.ttf","FontSize":32,"MaxWidth":200,"OutlineColor":"#000000","OutlineOpacity":100,"OutlineSize":4,"Text":{"Text":"HYSTERICAL","Type":0}},"Type":0,"X":-324,"Y":-284},{"Animations":[],"Children":[],"Conditions":[{"Code":"return $gameParty.members()[0] && $gameParty.members()[0].isStateAffected(8);","Type":9}],"CustomProperties":{},"ID":70,"Name":"Despair Check","Note":"","Opacity":1,"Rotation":0,"ScaleX":0.637255,"ScaleY":0.833333,"TextData":{"Alignment":1,"Color":"#01138a","FontFamily":"Gaegu-Bold.ttf","FontSize":32,"MaxWidth":200,"OutlineColor":"#000000","OutlineOpacity":100,"OutlineSize":4,"Text":{"Text":"DESPAIR","Type":0}},"Type":0,"X":-324,"Y":-284}],"Conditions":[{"Code":"return $gameParty.members()[0] && $gameParty.members()[0].isAlive();","Type":9}],"CustomProperties":{},"Expanded":false,"GroupData":{},"ID":350,"Name":"Is Alive","Note":"","Opacity":1,"Rotation":0,"Type":6,"X":412,"Y":445},{"Animations":[],"Children":[{"Animations":[],"CustomProperties":{},"ID":349,"Name":"Sleep - Copy 1","Note":"","Opacity":1,"Rotation":0,"ScaleX":0.628019,"ScaleY":0.792453,"TextData":{"Alignment":1,"Color":"#000000","FontFamily":"KleeOne-SemiBold.ttf","FontSize":32,"MaxWidth":200,"OutlineColor":"#bababa","OutlineOpacity":100,"OutlineSize":4,"Text":{"Text":"SLEEP","Type":0}},"Type":0,"X":-375,"Y":-335}],"Conditions":[{"Code":"return $gameParty.members()[0] && !$gameParty.members()[0].isAlive();","Type":9}],"CustomProperties":{},"Expanded":false,"GroupData":{},"ID":348,"Name":"Is Dead - Copy 4","Note":"","Opacity":1,"Rotation":0,"Type":6,"X":462,"Y":495}],"CustomProperties":{},"Expanded":false,"GroupData":{},"ID":42,"Name":"State Card","Note":"","Opacity":1,"Rotation":0,"Type":6,"X":-81,"Y":-148},{"Animations":[],"Children":[{"Animations":[],"CustomProperties":{},"ID":23,"Name":"Container","Note":"","Opacity":1,"Rotation":0,"ShapeData":{"Color":"#cfcfcf","Height":60,"OutlineColor":"#000000","OutlineOpacity":100,"OutlineSize":2,"Shape":0,"Width":144},"Type":1,"X":-43,"Y":0},{"Animations":[],"CustomProperties":{},"ID":25,"Name":"Hp Icon","Note":"","Opacity":1,"PictureData":{"Picture":"hp-icon"},"Rotation":0,"ScaleX":0.078,"ScaleY":0.07,"Type":2,"X":-95,"Y":-14},{"Animations":[],"CustomProperties":{},"GaugeData":{"BackgroundColor":"#333333","Color1":"#f02631","Color2":"#f02631","Height":20,"Maximum":{"ActorType":false,"Index":1,"Info":8,"Type":4},"OutlineColor":"#000000","OutlineOpacity":80,"OutlineSize":2,"Smoothness":20,"SyncComponent":"","Value":{"ActorType":false,"Index":1,"Info":3,"Type":4},"Width":100},"ID":29,"Name":"Hp Gauge","Note":"","Opacity":1,"Rotation":0,"Type":4,"X":-28,"Y":-14},{"Animations":[],"CustomProperties":{},"ID":33,"Name":"Hp/Mhp","Note":"","Opacity":1,"Rotation":0,"ScaleX":0.45098,"ScaleY":0.8235290000000001,"TextData":{"Alignment":2,"Color":"#ffffff","FontFamily":"Gaegu-Bold.ttf","FontSize":30,"MaxWidth":200,"OutlineColor":"#000000","OutlineOpacity":100,"OutlineSize":4,"Text":{"Code":"const member = $gameParty.members()[0];\nif (!member) return \"\";\nreturn member.hp + \"/\" + member.mhp;","Display":"(hp/mhp)","Type":7}},"Type":0,"X":-27,"Y":-14},{"Animations":[],"CustomProperties":{},"ID":20,"Name":"Mp Icon","Note":"","Opacity":1,"PictureData":{"Picture":"mp-icon"},"Rotation":0,"ScaleX":0.278,"ScaleY":0.22,"Type":2,"X":-95,"Y":13},{"Animations":[],"Children":[],"CustomProperties":{},"GaugeData":{"BackgroundColor":"#333333","Color1":"#11a7df","Color2":"#11a7df","Height":20,"Maximum":{"ActorType":false,"Index":1,"Info":9,"Type":4},"OutlineColor":"#000000","OutlineOpacity":80,"OutlineSize":2,"Smoothness":20,"SyncComponent":"","Value":{"ActorType":false,"Index":1,"Info":4,"Type":4},"Width":100},"ID":32,"Name":"Mana Gauge","Note":"","Opacity":1,"Rotation":0,"Type":4,"X":-28,"Y":13},{"Animations":[],"Children":[],"CustomProperties":{},"ID":34,"Name":"Mp/Mmp","Note":"","Opacity":1,"Rotation":0,"ScaleX":0.45,"ScaleY":0.823,"TextData":{"Alignment":2,"Color":"#ffffff","FontFamily":"Gaegu-Bold.ttf","FontSize":30,"MaxWidth":200,"OutlineColor":"#000000","OutlineOpacity":100,"OutlineSize":4,"Text":{"Code":"const member = $gameParty.members()[0];\nif (!member) return \"\";\nreturn member.mp + \"/\" + member.mmp;","Display":"(mp/mmp)","Type":7}},"Type":0,"X":-27,"Y":13}],"CustomProperties":{},"Expanded":false,"GroupData":{},"ID":30,"Name":"Status Card","Note":"","Opacity":1,"Rotation":0,"Type":6,"X":50,"Y":198}],"Conditions":[{"Code":"return $gameParty.members().length >= 1;","Type":9}],"CustomProperties":{},"Expanded":true,"GroupData":{},"ID":43,"Name":"Party 1","Note":"","Opacity":1,"Rotation":0,"Type":6,"X":77,"Y":14},{"Animations":[],"Children":[{"Animations":[{"ActivateType":{"RunType":1,"Type":0},"Duration":60,"EasingCurve":15,"EndOpacity":1,"Property":7,"Reset":true,"ReturnEasing":0,"StartOpacity":0,"Type":2}],"Children":[],"Conditions":[{"Code":"if (!$gameParty.inBattle() || BattleManager.actor() !== $gameParty.members()[1]) return false;\n    \nif (SceneManager._scene && SceneManager._scene._actorWindow && SceneManager._scene._actorWindow.active) return false;\n    \nreturn true;","Type":9}],"CustomProperties":{},"ID":308,"Name":"Whose turn is it? - Copy 1","Note":"","Opacity":1,"Rotation":0,"ShapeData":{"Color":"#ff0000","Height":240,"OutlineColor":"#000000","OutlineOpacity":100,"OutlineSize":2,"Shape":0,"Width":158},"Type":1,"X":7,"Y":117},{"Animations":[],"Children":[{"Animations":[],"Children":[],"CustomProperties":{},"ID":330,"Name":"Which ally? - Copy 1","Note":"","Opacity":1,"Rotation":0,"ShapeData":{"Color":"#00ff00","Height":238,"OutlineColor":"#000000","OutlineOpacity":100,"OutlineSize":2,"Shape":0,"Width":158},"Type":1,"X":-106,"Y":-201},{"Animations":[{"ActivateType":{"RunType":1,"Type":0},"Duration":60,"EasingCurve":12,"EndY":-45,"Property":1,"Reset":true,"ReturnEasing":0,"StartY":-60,"Type":2}],"CustomProperties":{},"ID":319,"Name":"Cursor Pointer - Copy 1","Note":"","Opacity":1,"PictureData":{"Picture":"finger_up"},"Rotation":0,"ScaleX":1.625,"ScaleY":1.625,"Type":2,"X":-106,"Y":-60}],"Conditions":[{"Code":"try {\n    if (!$gameParty.inBattle() || !SceneManager._scene || !SceneManager._scene._actorWindow) return false;\n    return SceneManager._scene._actorWindow.active && SceneManager._scene._actorWindow.index() === 1;\n} catch (e) {\n    return false;\n}","Type":9}],"CustomProperties":{},"Expanded":true,"GroupData":{},"ID":317,"Name":"Targeted as Ally","Note":"","Opacity":1,"Rotation":0,"Type":6,"X":113,"Y":318},{"Animations":[],"Children":[{"Animations":[],"CustomProperties":{},"ID":213,"Name":"OuContainer - Copy 1","Note":"","Opacity":1,"Rotation":0,"ShapeData":{"Color":"#ffffff","Height":156,"OutlineColor":"#000000","OutlineOpacity":100,"OutlineSize":2,"Shape":0,"Width":144},"Type":1,"X":7,"Y":15},{"Animations":[],"Children":[],"CustomProperties":{},"ID":362,"Name":"InContainer - Copy 4","Note":"","Opacity":1,"Rotation":0,"ShapeData":{"Color":"#ffffff","Height":134,"OutlineColor":"#000000","OutlineOpacity":100,"OutlineSize":2,"Shape":0,"Width":132},"Type":1,"X":7,"Y":18},{"Animations":[],"Children":[],"CustomProperties":{},"ID":361,"Name":"Actor Face - Copy 4","Note":"","Opacity":1,"PictureData":{"Code":"let actor = $gameParty.battleMembers()[1];\n\nlet aName = actor.name().replace(/\\\\[a-zA-Z]+\\[.*?\\]/g, '').replace(/[\\x00-\\x1F\\x7F-\\x9F]/g, '').trim().toLowerCase();\n\nlet stateStr = \"neutral\";\n\nif (actor.isDead()) {\n    stateStr = \"sleep\";\n} else if (actor.isStateAffected(3)) {\n    stateStr = \"heroic\";\n} else if (actor.isStateAffected(4)) {\n    stateStr = \"frantic\";\n} else if (actor.isStateAffected(5)) {\n    stateStr = \"hopeless\";\n} else if (actor.isStateAffected(6)) {\n    stateStr = \"martyr\";\n} else if (actor.isStateAffected(7)) {\n    stateStr = \"hysterical\";\n} else if (actor.isStateAffected(8)) {\n    stateStr = \"despair\";\n}\n\nreturn \"img/pictures/\" + aName + \"_\" + stateStr + \"_state.png\";","Picture":""},"Rotation":0,"ScaleX":0.5,"ScaleY":0.5,"Type":2,"X":7,"Y":18}],"CustomProperties":{},"Expanded":true,"GroupData":{},"ID":212,"Name":"Actor Card - Copy 1","Note":"","Opacity":1,"Rotation":0,"Type":6,"X":0,"Y":76},{"Animations":[],"Children":[{"Animations":[],"Children":[],"CustomProperties":{},"ID":363,"Name":"InContainer - Copy 1","Note":"","Opacity":1,"Rotation":0,"ShapeData":{"Color":"#ffffff","Height":32,"OutlineColor":"#000000","OutlineOpacity":100,"OutlineSize":2,"Shape":0,"Width":132},"Type":1,"X":88,"Y":161},{"Animations":[],"Children":[{"Animations":[],"Conditions":[{"Code":"const actor = $gameParty.members()[1];\nif (!actor) return false;\n\nconst emotionStates = [3, 4, 5, 6, 7, 8]; \n\nreturn !emotionStates.some(id => actor.isStateAffected(id));","Type":9}],"CustomProperties":{},"ID":219,"Name":"Neutral Check - Copy 1","Note":"","Opacity":1,"Rotation":0,"ScaleX":0.627451,"ScaleY":0.833333,"TextData":{"Alignment":1,"Color":"#ffffff","FontFamily":"Gaegu-Bold.ttf","FontSize":32,"MaxWidth":200,"OutlineColor":"#000000","OutlineOpacity":100,"OutlineSize":7,"Text":{"Text":"NEUTRAL","Type":0}},"Type":0,"X":326,"Y":-284},{"Animations":[],"Children":[],"Conditions":[{"Code":"return $gameParty.members()[1] && $gameParty.members()[1].isStateAffected(3);","Type":9}],"CustomProperties":{},"ID":220,"Name":"Heroic Check - Copy 1","Note":"","Opacity":1,"Rotation":0,"ScaleX":0.627451,"ScaleY":0.833333,"TextData":{"Alignment":1,"Color":"#ffff00","FontFamily":"Gaegu-Bold.ttf","FontSize":32,"MaxWidth":200,"OutlineColor":"#000000","OutlineOpacity":100,"OutlineSize":4,"Text":{"Text":"HEROIC","Type":0}},"Type":0,"X":326,"Y":-284},{"Animations":[],"Children":[],"Conditions":[{"Code":"return $gameParty.members()[1] && $gameParty.members()[1].isStateAffected(3);","Type":9}],"CustomProperties":{},"ID":280,"Name":"Heroic Turns","Note":"","Opacity":1,"Rotation":0,"ScaleX":0.5,"ScaleY":0.5,"TextData":{"Alignment":1,"Color":"#ffff00","FontFamily":"Gaegu-Bold.ttf","FontSize":32,"MaxWidth":200,"OutlineColor":"#000000","OutlineOpacity":100,"OutlineSize":4,"Text":{"Code":"var actor = $gameParty.members()[1]\nvar stateId = 3; \n\nif (actor && actor.isStateAffected(stateId)) {\n    return actor.stateTurns(stateId);\n} else {\n    return \"\";\n}","Display":"(code)","Type":7}},"Type":0,"X":361,"Y":-291},{"Animations":[],"Children":[],"Conditions":[{"Code":"return $gameParty.members()[1] && $gameParty.members()[1].isStateAffected(4);","Type":9}],"CustomProperties":{},"ID":221,"Name":"Frantic Check - Copy 1","Note":"","Opacity":1,"Rotation":0,"ScaleX":0.627451,"ScaleY":0.833333,"TextData":{"Alignment":1,"Color":"#ff0000","FontFamily":"Gaegu-Bold.ttf","FontSize":32,"MaxWidth":200,"OutlineColor":"#000000","OutlineOpacity":100,"OutlineSize":4,"Text":{"Text":"FRANTIC","Type":0}},"Type":0,"X":326,"Y":-284},{"Animations":[],"Children":[],"Conditions":[{"Code":"return $gameParty.members()[1] && $gameParty.members()[1].isStateAffected(5);","Type":9}],"CustomProperties":{},"ID":222,"Name":"Hopeless Check - Copy 1","Note":"","Opacity":1,"Rotation":0,"ScaleX":0.627451,"ScaleY":0.833333,"TextData":{"Alignment":1,"Color":"#0223ff","FontFamily":"Gaegu-Bold.ttf","FontSize":32,"MaxWidth":200,"OutlineColor":"#000000","OutlineOpacity":100,"OutlineSize":4,"Text":{"Text":"HOPELESS","Type":0}},"Type":0,"X":326,"Y":-284},{"Animations":[],"Children":[],"Conditions":[{"Code":"return $gameParty.members()[1] && $gameParty.members()[1].isStateAffected(6);","Type":9}],"CustomProperties":{},"ID":223,"Name":"Martyr Check - Copy 1","Note":"","Opacity":1,"Rotation":0,"ScaleX":0.656863,"ScaleY":0.833333,"TextData":{"Alignment":1,"Color":"#a9ac00","FontFamily":"Gaegu-Bold.ttf","FontSize":32,"MaxWidth":200,"OutlineColor":"#000000","OutlineOpacity":100,"OutlineSize":4,"Text":{"Text":"MARTYR","Type":0}},"Type":0,"X":326,"Y":-284},{"Animations":[],"Children":[],"Conditions":[{"Code":"return $gameParty.members()[1] && $gameParty.members()[1].isStateAffected(7);","Type":9}],"CustomProperties":{},"ID":224,"Name":"Hysterical Check - Copy 1","Note":"","Opacity":1,"Rotation":0,"ScaleX":0.627451,"ScaleY":0.833333,"TextData":{"Alignment":1,"Color":"#ff0000","FontFamily":"Gaegu-Bold.ttf","FontSize":32,"MaxWidth":200,"OutlineColor":"#000000","OutlineOpacity":100,"OutlineSize":4,"Text":{"Text":"HYSTERICAL","Type":0}},"Type":0,"X":326,"Y":-284},{"Animations":[],"Children":[],"Conditions":[{"Code":"return $gameParty.members()[1] && $gameParty.members()[1].isStateAffected(8);","Type":9}],"CustomProperties":{},"ID":225,"Name":"Despair Check - Copy 1","Note":"","Opacity":1,"Rotation":0,"ScaleX":0.637255,"ScaleY":0.833333,"TextData":{"Alignment":1,"Color":"#01138a","FontFamily":"Gaegu-Bold.ttf","FontSize":32,"MaxWidth":200,"OutlineColor":"#000000","OutlineOpacity":100,"OutlineSize":4,"Text":{"Text":"DESPAIR","Type":0}},"Type":0,"X":326,"Y":-284}],"Conditions":[{"Code":"return $gameParty.members()[1] && $gameParty.members()[1].isAlive();","Type":9}],"CustomProperties":{},"Expanded":true,"GroupData":{},"ID":338,"Name":"Is Alive","Note":"","Opacity":1,"Rotation":0,"Type":6,"X":-238,"Y":445},{"Animations":[],"Children":[{"Animations":[],"CustomProperties":{},"ID":340,"Name":"Sleep","Note":"","Opacity":1,"Rotation":0,"ScaleX":0.628019,"ScaleY":0.792453,"TextData":{"Alignment":1,"Color":"#000000","FontFamily":"KleeOne-SemiBold.ttf","FontSize":32,"MaxWidth":200,"OutlineColor":"#bababa","OutlineOpacity":100,"OutlineSize":4,"Text":{"Text":"SLEEP","Type":0}},"Type":0,"X":326,"Y":-284}],"Conditions":[{"Code":"return $gameParty.members()[1] && !$gameParty.members()[1].isAlive();","Type":9}],"CustomProperties":{},"Expanded":true,"GroupData":{},"ID":339,"Name":"Is Dead","Note":"","Opacity":1,"Rotation":0,"Type":6,"X":-238,"Y":445}],"CustomProperties":{},"Expanded":true,"GroupData":{},"ID":216,"Name":"State Card - Copy 1","Note":"","Opacity":1,"Rotation":0,"Type":6,"X":-81,"Y":-147},{"Animations":[],"Children":[{"Animations":[],"CustomProperties":{},"ID":227,"Name":"Container - Copy 1","Note":"","Opacity":1,"Rotation":0,"ShapeData":{"Color":"#cfcfcf","Height":60,"OutlineColor":"#000000","OutlineOpacity":100,"OutlineSize":2,"Shape":0,"Width":144},"Type":1,"X":-43,"Y":0},{"Animations":[],"CustomProperties":{},"ID":228,"Name":"Hp Icon - Copy 1","Note":"","Opacity":1,"PictureData":{"Picture":"hp-icon"},"Rotation":0,"ScaleX":0.078,"ScaleY":0.07,"Type":2,"X":-95,"Y":-14},{"Animations":[],"CustomProperties":{},"GaugeData":{"BackgroundColor":"#333333","Color1":"#f02631","Color2":"#f02631","Height":20,"Maximum":{"ActorType":false,"Index":2,"Info":8,"Type":4},"OutlineColor":"#000000","OutlineOpacity":80,"OutlineSize":2,"Smoothness":20,"SyncComponent":"","Value":{"ActorType":false,"Index":2,"Info":3,"Type":4},"Width":100},"ID":229,"Name":"Hp Gauge - Copy 1","Note":"","Opacity":1,"Rotation":0,"Type":4,"X":-28,"Y":-14},{"Animations":[],"CustomProperties":{},"ID":230,"Name":"Hp/Mhp - Copy 1","Note":"","Opacity":1,"Rotation":0,"ScaleX":0.45098,"ScaleY":0.8235290000000001,"TextData":{"Alignment":2,"Color":"#ffffff","FontFamily":"Gaegu-Bold.ttf","FontSize":30,"MaxWidth":200,"OutlineColor":"#000000","OutlineOpacity":100,"OutlineSize":4,"Text":{"Code":"const member = $gameParty.members()[1];\nif (!member) return \"\";\nreturn member.hp + \"/\" + member.mhp;","Display":"(hp/mhp)","Type":7}},"Type":0,"X":-27,"Y":-14},{"Animations":[],"CustomProperties":{},"ID":231,"Name":"Mp Icon - Copy 1","Note":"","Opacity":1,"PictureData":{"Picture":"mp-icon"},"Rotation":0,"ScaleX":0.278,"ScaleY":0.22,"Type":2,"X":-95,"Y":13},{"Animations":[],"Children":[],"CustomProperties":{},"GaugeData":{"BackgroundColor":"#333333","Color1":"#11a7df","Color2":"#11a7df","Height":20,"Maximum":{"ActorType":false,"Index":2,"Info":9,"Type":4},"OutlineColor":"#000000","OutlineOpacity":80,"OutlineSize":2,"Smoothness":20,"SyncComponent":"","Value":{"ActorType":false,"Index":2,"Info":4,"Type":4},"Width":100},"ID":232,"Name":"Mana Gauge - Copy 1","Note":"","Opacity":1,"Rotation":0,"Type":4,"X":-28,"Y":13},{"Animations":[],"Children":[],"CustomProperties":{},"ID":233,"Name":"Mp/Mmp - Copy 1","Note":"","Opacity":1,"Rotation":0,"ScaleX":0.45,"ScaleY":0.823,"TextData":{"Alignment":2,"Color":"#ffffff","FontFamily":"Gaegu-Bold.ttf","FontSize":30,"MaxWidth":200,"OutlineColor":"#000000","OutlineOpacity":100,"OutlineSize":4,"Text":{"Code":"const member = $gameParty.members()[1];\nif (!member) return \"\";\nreturn member.mp + \"/\" + member.mmp;","Display":"(mp/mmp)","Type":7}},"Type":0,"X":-27,"Y":13}],"CustomProperties":{},"Expanded":true,"GroupData":{},"ID":226,"Name":"Status Card - Copy 1","Note":"","Opacity":1,"Rotation":0,"Type":6,"X":50,"Y":198}],"Conditions":[{"Code":"return $gameParty.members().length >= 2;","Type":9}],"CustomProperties":{},"Expanded":true,"GroupData":{},"ID":211,"Name":"Party 2","Note":"","Opacity":1,"Rotation":0,"Type":6,"X":727,"Y":14},{"Animations":[],"Children":[{"Animations":[{"ActivateType":{"RunType":1,"Type":0},"Duration":60,"EasingCurve":15,"EndOpacity":1,"Property":7,"Reset":true,"ReturnEasing":0,"StartOpacity":0,"Type":2}],"Children":[],"Conditions":[{"Code":"if (!$gameParty.inBattle() || BattleManager.actor() !== $gameParty.members()[2]) return false;\n    \nif (SceneManager._scene && SceneManager._scene._actorWindow && SceneManager._scene._actorWindow.active) return false;\n    \nreturn true;","Type":9}],"CustomProperties":{},"ID":309,"Name":"Whose turn is it? - Copy 2","Note":"","Opacity":1,"Rotation":0,"ShapeData":{"Color":"#ff0000","Height":238,"OutlineColor":"#000000","OutlineOpacity":100,"OutlineSize":2,"Shape":0,"Width":158},"Type":1,"X":7,"Y":116},{"Animations":[],"Children":[{"Animations":[],"Children":[],"CustomProperties":{},"ID":331,"Name":"Which ally? - Copy 2","Note":"","Opacity":1,"Rotation":0,"ShapeData":{"Color":"#00ff00","Height":240,"OutlineColor":"#000000","OutlineOpacity":100,"OutlineSize":2,"Shape":0,"Width":158},"Type":1,"X":-323,"Y":-153},{"Animations":[{"ActivateType":{"RunType":1,"Type":0},"Duration":60,"EasingCurve":12,"EndY":-306,"Property":1,"Reset":true,"ReturnEasing":0,"StartY":-291,"Type":2}],"CustomProperties":{},"ID":322,"Name":"Cursor Pointer - Copy 2","Note":"","Opacity":1,"PictureData":{"Picture":"finger_down"},"Rotation":0,"ScaleX":1.625,"ScaleY":1.625,"Type":2,"X":-321,"Y":-291}],"Conditions":[{"Code":"try {\n    if (!$gameParty.inBattle() || !SceneManager._scene || !SceneManager._scene._actorWindow) return false;\n    return SceneManager._scene._actorWindow.active && SceneManager._scene._actorWindow.index() === 2;\n} catch (e) {\n    return false;\n}","Type":9}],"CustomProperties":{},"Expanded":true,"GroupData":{},"ID":320,"Name":"Targetted as Ally","Note":"","Opacity":1,"Rotation":0,"Type":6,"X":330,"Y":269},{"Animations":[],"Children":[{"Animations":[],"CustomProperties":{},"ID":236,"Name":"OuContainer - Copy 3","Note":"","Opacity":1,"Rotation":0,"ShapeData":{"Color":"#ffffff","Height":156,"OutlineColor":"#000000","OutlineOpacity":100,"OutlineSize":2,"Shape":0,"Width":144},"Type":1,"X":7,"Y":15},{"Animations":[],"Children":[],"CustomProperties":{},"ID":366,"Name":"InContainer - Copy 3","Note":"","Opacity":1,"Rotation":0,"ShapeData":{"Color":"#ffffff","Height":130,"OutlineColor":"#000000","OutlineOpacity":100,"OutlineSize":2,"Shape":0,"Width":132},"Type":1,"X":7,"Y":17},{"Animations":[],"Children":[],"CustomProperties":{},"ID":365,"Name":"Actor Face - Copy 1","Note":"","Opacity":1,"PictureData":{"Code":"let actor = $gameParty.battleMembers()[2];\n\nlet aName = actor.name().replace(/\\\\[a-zA-Z]+\\[.*?\\]/g, '').replace(/[\\x00-\\x1F\\x7F-\\x9F]/g, '').trim().toLowerCase();\n\nlet stateStr = \"neutral\";\n\nif (actor.isDead()) {\n    stateStr = \"sleep\";\n} else if (actor.isStateAffected(3)) {\n    stateStr = \"heroic\";\n} else if (actor.isStateAffected(4)) {\n    stateStr = \"frantic\";\n} else if (actor.isStateAffected(5)) {\n    stateStr = \"hopeless\";\n} else if (actor.isStateAffected(6)) {\n    stateStr = \"martyr\";\n} else if (actor.isStateAffected(7)) {\n    stateStr = \"hysterical\";\n} else if (actor.isStateAffected(8)) {\n    stateStr = \"despair\";\n}\n\nreturn \"img/pictures/\" + aName + \"_\" + stateStr + \"_state.png\";","Picture":""},"Rotation":0,"ScaleX":0.5,"ScaleY":0.5,"Type":2,"X":7,"Y":16}],"CustomProperties":{},"Expanded":true,"GroupData":{},"ID":235,"Name":"Actor Card - Copy 2","Note":"","Opacity":1,"Rotation":0,"Type":6,"X":0,"Y":76},{"Animations":[],"Children":[{"Animations":[],"Children":[],"CustomProperties":{},"ID":367,"Name":"InContainer - Copy 6","Note":"","Opacity":1,"Rotation":0,"ShapeData":{"Color":"#ffffff","Height":32,"OutlineColor":"#000000","OutlineOpacity":100,"OutlineSize":2,"Shape":0,"Width":132},"Type":1,"X":88,"Y":161},{"Animations":[],"Children":[{"Animations":[],"Conditions":[{"Code":"const actor = $gameParty.members()[2];\nif (!actor) return false;\n\nconst emotionStates = [3, 4, 5, 6, 7, 8]; \n\nreturn !emotionStates.some(id => actor.isStateAffected(id));","Type":9}],"CustomProperties":{},"ID":242,"Name":"Neutral Check - Copy 2","Note":"","Opacity":1,"Rotation":0,"ScaleX":0.627451,"ScaleY":0.833333,"TextData":{"Alignment":1,"Color":"#ffffff","FontFamily":"Gaegu-Bold.ttf","FontSize":32,"MaxWidth":200,"OutlineColor":"#000000","OutlineOpacity":100,"OutlineSize":7,"Text":{"Text":"NEUTRAL","Type":0}},"Type":0,"X":-324,"Y":81},{"Animations":[],"Children":[],"Conditions":[{"Code":"return $gameParty.members()[2] && $gameParty.members()[2].isStateAffected(3);","Type":9}],"CustomProperties":{},"ID":243,"Name":"Heroic Check - Copy 2","Note":"","Opacity":1,"Rotation":0,"ScaleX":0.627451,"ScaleY":0.833333,"TextData":{"Alignment":1,"Color":"#ffff00","FontFamily":"Gaegu-Bold.ttf","FontSize":32,"MaxWidth":200,"OutlineColor":"#000000","OutlineOpacity":100,"OutlineSize":4,"Text":{"Text":"HEROIC","Type":0}},"Type":0,"X":-324,"Y":81},{"Animations":[],"Children":[],"Conditions":[{"Code":"return $gameParty.members()[2] && $gameParty.members()[2].isStateAffected(3);","Type":9}],"CustomProperties":{},"ID":282,"Name":"Heroic Turns - Copy 2","Note":"","Opacity":1,"Rotation":0,"ScaleX":0.5,"ScaleY":0.5,"TextData":{"Alignment":1,"Color":"#ffff00","FontFamily":"Gaegu-Bold.ttf","FontSize":32,"MaxWidth":200,"OutlineColor":"#000000","OutlineOpacity":100,"OutlineSize":4,"Text":{"Code":"var actor = $gameParty.members()[2]\nvar stateId = 3; \n\nif (actor && actor.isStateAffected(stateId)) {\n    return actor.stateTurns(stateId);\n} else {\n    return \"\";\n}","Display":"(code)","Type":7}},"Type":0,"X":-289,"Y":74},{"Animations":[],"Children":[],"Conditions":[{"Code":"return $gameParty.members()[2] && $gameParty.members()[2].isStateAffected(4);","Type":9}],"CustomProperties":{},"ID":244,"Name":"Frantic Check - Copy 2","Note":"","Opacity":1,"Rotation":0,"ScaleX":0.627451,"ScaleY":0.833333,"TextData":{"Alignment":1,"Color":"#ff0000","FontFamily":"Gaegu-Bold.ttf","FontSize":32,"MaxWidth":200,"OutlineColor":"#000000","OutlineOpacity":100,"OutlineSize":4,"Text":{"Text":"FRANTIC","Type":0}},"Type":0,"X":-324,"Y":81},{"Animations":[],"Children":[],"Conditions":[{"Code":"return $gameParty.members()[2] && $gameParty.members()[2].isStateAffected(5);","Type":9}],"CustomProperties":{},"ID":245,"Name":"Hopeless Check - Copy 2","Note":"","Opacity":1,"Rotation":0,"ScaleX":0.627451,"ScaleY":0.833333,"TextData":{"Alignment":1,"Color":"#0223ff","FontFamily":"Gaegu-Bold.ttf","FontSize":32,"MaxWidth":200,"OutlineColor":"#000000","OutlineOpacity":100,"OutlineSize":4,"Text":{"Text":"HOPELESS","Type":0}},"Type":0,"X":-324,"Y":81},{"Animations":[],"Children":[],"Conditions":[{"Code":"return $gameParty.members()[2] && $gameParty.members()[2].isStateAffected(7);","Type":9}],"CustomProperties":{},"ID":247,"Name":"Hysterical Check - Copy 2","Note":"","Opacity":1,"Rotation":0,"ScaleX":0.627451,"ScaleY":0.833333,"TextData":{"Alignment":1,"Color":"#ff0000","FontFamily":"Gaegu-Bold.ttf","FontSize":32,"MaxWidth":200,"OutlineColor":"#000000","OutlineOpacity":100,"OutlineSize":4,"Text":{"Text":"HYSTERICAL","Type":0}},"Type":0,"X":-324,"Y":81},{"Animations":[],"Children":[],"Conditions":[{"Code":"return $gameParty.members()[2] && $gameParty.members()[2].isStateAffected(6);","Type":9}],"CustomProperties":{},"ID":246,"Name":"Martyr Check - Copy 2","Note":"","Opacity":1,"Rotation":0,"ScaleX":0.656863,"ScaleY":0.833333,"TextData":{"Alignment":1,"Color":"#a9ac00","FontFamily":"Gaegu-Bold.ttf","FontSize":32,"MaxWidth":200,"OutlineColor":"#000000","OutlineOpacity":100,"OutlineSize":4,"Text":{"Text":"MARTYR","Type":0}},"Type":0,"X":-324,"Y":81},{"Animations":[],"Children":[],"Conditions":[{"Code":"return $gameParty.members()[2] && $gameParty.members()[2].isStateAffected(8);","Type":9}],"CustomProperties":{},"ID":248,"Name":"Despair Check - Copy 2","Note":"","Opacity":1,"Rotation":0,"ScaleX":0.637255,"ScaleY":0.833333,"TextData":{"Alignment":1,"Color":"#01138a","FontFamily":"Gaegu-Bold.ttf","FontSize":32,"MaxWidth":200,"OutlineColor":"#000000","OutlineOpacity":100,"OutlineSize":4,"Text":{"Text":"DESPAIR","Type":0}},"Type":0,"X":-322,"Y":83}],"Conditions":[{"Code":"return $gameParty.members()[2] && $gameParty.members()[2].isAlive();","Type":9}],"CustomProperties":{},"Expanded":false,"GroupData":{},"ID":353,"Name":"Is Alive","Note":"","Opacity":1,"Rotation":0,"Type":6,"X":412,"Y":78},{"Animations":[],"Children":[{"Animations":[],"Children":[],"CustomProperties":{},"ID":358,"Name":"Sleep - Copy 2","Note":"","Opacity":1,"Rotation":0,"ScaleX":0.628019,"ScaleY":0.792453,"TextData":{"Alignment":1,"Color":"#000000","FontFamily":"KleeOne-SemiBold.ttf","FontSize":32,"MaxWidth":200,"OutlineColor":"#bababa","OutlineOpacity":100,"OutlineSize":4,"Text":{"Text":"SLEEP","Type":0}},"Type":0,"X":-310,"Y":160}],"Conditions":[{"Code":"return $gameParty.members()[2] && !$gameParty.members()[2].isAlive();","Type":9}],"CustomProperties":{},"Expanded":true,"GroupData":{},"ID":351,"Name":"Is Dead - Copy 5","Note":"","Opacity":1,"Rotation":0,"Type":6,"X":397,"Y":-2}],"CustomProperties":{},"Expanded":true,"GroupData":{},"ID":239,"Name":"State Card - Copy 2","Note":"","Opacity":1,"Rotation":0,"Type":6,"X":-81,"Y":-147},{"Animations":[],"Children":[{"Animations":[],"CustomProperties":{},"ID":250,"Name":"Container - Copy 2","Note":"","Opacity":1,"Rotation":0,"ShapeData":{"Color":"#cfcfcf","Height":60,"OutlineColor":"#000000","OutlineOpacity":100,"OutlineSize":2,"Shape":0,"Width":144},"Type":1,"X":-43,"Y":0},{"Animations":[],"CustomProperties":{},"ID":251,"Name":"Hp Icon - Copy 2","Note":"","Opacity":1,"PictureData":{"Picture":"hp-icon"},"Rotation":0,"ScaleX":0.078,"ScaleY":0.07,"Type":2,"X":-95,"Y":-14},{"Animations":[],"CustomProperties":{},"GaugeData":{"BackgroundColor":"#333333","Color1":"#f02631","Color2":"#f02631","Height":20,"Maximum":{"ActorType":false,"Index":3,"Info":8,"Type":4},"OutlineColor":"#000000","OutlineOpacity":80,"OutlineSize":2,"Smoothness":20,"SyncComponent":"","Value":{"ActorType":false,"Index":3,"Info":3,"Type":4},"Width":100},"ID":252,"Name":"Hp Gauge - Copy 2","Note":"","Opacity":1,"Rotation":0,"Type":4,"X":-28,"Y":-14},{"Animations":[],"CustomProperties":{},"ID":253,"Name":"Hp/Mhp - Copy 2","Note":"","Opacity":1,"Rotation":0,"ScaleX":0.45098,"ScaleY":0.8235290000000001,"TextData":{"Alignment":2,"Color":"#ffffff","FontFamily":"Gaegu-Bold.ttf","FontSize":30,"MaxWidth":200,"OutlineColor":"#000000","OutlineOpacity":100,"OutlineSize":4,"Text":{"Code":"const member = $gameParty.members()[2];\nif (!member) return \"\";\nreturn member.hp + \"/\" + member.mhp;","Display":"(hp/mhp)","Type":7}},"Type":0,"X":-27,"Y":-14},{"Animations":[],"CustomProperties":{},"ID":254,"Name":"Mp Icon - Copy 2","Note":"","Opacity":1,"PictureData":{"Picture":"mp-icon"},"Rotation":0,"ScaleX":0.278,"ScaleY":0.22,"Type":2,"X":-95,"Y":13},{"Animations":[],"Children":[],"CustomProperties":{},"GaugeData":{"BackgroundColor":"#333333","Color1":"#11a7df","Color2":"#11a7df","Height":20,"Maximum":{"ActorType":false,"Index":3,"Info":9,"Type":4},"OutlineColor":"#000000","OutlineOpacity":80,"OutlineSize":2,"Smoothness":20,"SyncComponent":"","Value":{"ActorType":false,"Index":3,"Info":4,"Type":4},"Width":100},"ID":255,"Name":"Mana Gauge - Copy 2","Note":"","Opacity":1,"Rotation":0,"Type":4,"X":-28,"Y":13},{"Animations":[],"Children":[],"CustomProperties":{},"ID":256,"Name":"Mp/Mmp - Copy 2","Note":"","Opacity":1,"Rotation":0,"ScaleX":0.45,"ScaleY":0.823,"TextData":{"Alignment":2,"Color":"#ffffff","FontFamily":"Gaegu-Bold.ttf","FontSize":30,"MaxWidth":200,"OutlineColor":"#000000","OutlineOpacity":100,"OutlineSize":4,"Text":{"Code":"const member = $gameParty.members()[2];\nif (!member) return \"\";\nreturn member.mp + \"/\" + member.mmp;","Display":"(mp/mmp)","Type":7}},"Type":0,"X":-27,"Y":13}],"CustomProperties":{},"Expanded":false,"GroupData":{},"ID":249,"Name":"Status Card - Copy 2","Note":"","Opacity":1,"Rotation":0,"Type":6,"X":50,"Y":198}],"Conditions":[{"Code":"return $gameParty.members().length >= 3;","Type":9}],"CustomProperties":{},"Expanded":true,"GroupData":{},"ID":234,"Name":"Party 3","Note":"","Opacity":1,"Rotation":0,"Type":6,"X":77,"Y":379},{"Animations":[],"Children":[{"Animations":[{"ActivateType":{"RunType":1,"Type":0},"Duration":60,"EasingCurve":15,"EndOpacity":1,"Property":7,"Reset":true,"ReturnEasing":0,"StartOpacity":0,"Type":2}],"Children":[],"Conditions":[{"Code":"if (!$gameParty.inBattle() || BattleManager.actor() !== $gameParty.members()[3]) return false;\n    \nif (SceneManager._scene && SceneManager._scene._actorWindow && SceneManager._scene._actorWindow.active) return false;\n    \nreturn true;","Type":9}],"CustomProperties":{},"ID":310,"Name":"Whose turn is it? - Copy 3","Note":"","Opacity":1,"Rotation":0,"ShapeData":{"Color":"#ff0000","Height":240,"OutlineColor":"#000000","OutlineOpacity":100,"OutlineSize":2,"Shape":0,"Width":158},"Type":1,"X":7,"Y":116},{"Animations":[],"Children":[{"Animations":[],"Children":[],"CustomProperties":{},"ID":332,"Name":"Which ally? - Copy 3","Note":"","Opacity":1,"Rotation":0,"ShapeData":{"Color":"#00ff00","Height":238,"OutlineColor":"#000000","OutlineOpacity":100,"OutlineSize":2,"Shape":0,"Width":156},"Type":1,"X":-106,"Y":-153},{"Animations":[{"ActivateType":{"RunType":1,"Type":0},"Duration":60,"EasingCurve":12,"EndY":-307,"Property":1,"Reset":true,"ReturnEasing":0,"StartY":-292,"Type":2}],"CustomProperties":{},"ID":328,"Name":"Cursor Pointer - Copy 3","Note":"","Opacity":1,"PictureData":{"Picture":"finger_down"},"Rotation":0,"ScaleX":1.625,"ScaleY":1.625,"Type":2,"X":-105,"Y":-292}],"Conditions":[{"Code":"try {\n    if (!$gameParty.inBattle() || !SceneManager._scene || !SceneManager._scene._actorWindow) return false;\n    return SceneManager._scene._actorWindow.active && SceneManager._scene._actorWindow.index() === 3;\n} catch (e) {\n    return false;\n}","Type":9}],"CustomProperties":{},"Expanded":false,"GroupData":{},"ID":326,"Name":"Targetted as Ally","Note":"","Opacity":1,"Rotation":0,"Type":6,"X":113,"Y":269},{"Animations":[],"Children":[{"Animations":[],"CustomProperties":{},"ID":259,"Name":"OuContainer - Copy 5","Note":"","Opacity":1,"Rotation":0,"ShapeData":{"Color":"#ffffff","Height":156,"OutlineColor":"#000000","OutlineOpacity":100,"OutlineSize":2,"Shape":0,"Width":144},"Type":1,"X":7,"Y":15},{"Animations":[],"Children":[],"CustomProperties":{},"ID":369,"Name":"InContainer - Copy 5","Note":"","Opacity":1,"Rotation":0,"ShapeData":{"Color":"#ffffff","Height":130,"OutlineColor":"#000000","OutlineOpacity":100,"OutlineSize":2,"Shape":0,"Width":132},"Type":1,"X":7,"Y":18},{"Animations":[],"Children":[],"CustomProperties":{},"ID":368,"Name":"Actor Face - Copy 2","Note":"","Opacity":1,"PictureData":{"Code":"let actor = $gameParty.battleMembers()[3];\n\nlet aName = actor.name().replace(/\\\\[a-zA-Z]+\\[.*?\\]/g, '').replace(/[\\x00-\\x1F\\x7F-\\x9F]/g, '').trim().toLowerCase();\n\nlet stateStr = \"neutral\";\n\nif (actor.isDead()) {\n    stateStr = \"sleep\";\n} else if (actor.isStateAffected(3)) {\n    stateStr = \"heroic\";\n} else if (actor.isStateAffected(4)) {\n    stateStr = \"frantic\";\n} else if (actor.isStateAffected(5)) {\n    stateStr = \"hopeless\";\n} else if (actor.isStateAffected(6)) {\n    stateStr = \"martyr\";\n} else if (actor.isStateAffected(7)) {\n    stateStr = \"hysterical\";\n} else if (actor.isStateAffected(8)) {\n    stateStr = \"despair\";\n}\n\nreturn \"img/pictures/\" + aName + \"_\" + stateStr + \"_state.png\";","Picture":""},"Rotation":0,"ScaleX":0.5,"ScaleY":0.5,"Type":2,"X":7,"Y":17}],"CustomProperties":{},"Expanded":true,"GroupData":{},"ID":258,"Name":"Actor Card - Copy 3","Note":"","Opacity":1,"Rotation":0,"Type":6,"X":0,"Y":76},{"Animations":[],"Children":[{"Animations":[],"Children":[],"CustomProperties":{},"ID":370,"Name":"InContainer - Copy 7","Note":"","Opacity":1,"Rotation":0,"ShapeData":{"Color":"#ffffff","Height":34,"OutlineColor":"#000000","OutlineOpacity":100,"OutlineSize":2,"Shape":0,"Width":132},"Type":1,"X":88,"Y":160},{"Animations":[],"Children":[{"Animations":[],"Conditions":[{"Code":"const actor = $gameParty.members()[3];\nif (!actor) return false;\n\nconst emotionStates = [3, 4, 5, 6, 7, 8]; \n\nreturn !emotionStates.some(id => actor.isStateAffected(id));","Type":9}],"CustomProperties":{},"ID":265,"Name":"Neutral Check - Copy 3","Note":"","Opacity":1,"Rotation":0,"ScaleX":0.627451,"ScaleY":0.833333,"TextData":{"Alignment":1,"Color":"#ffffff","FontFamily":"Gaegu-Bold.ttf","FontSize":32,"MaxWidth":200,"OutlineColor":"#000000","OutlineOpacity":100,"OutlineSize":7,"Text":{"Text":"NEUTRAL","Type":0}},"Type":0,"X":326,"Y":81},{"Animations":[],"Children":[],"Conditions":[{"Code":"return $gameParty.members()[3] && $gameParty.members()[3].isStateAffected(3);","Type":9}],"CustomProperties":{},"ID":266,"Name":"Heroic Check - Copy 3","Note":"","Opacity":1,"Rotation":0,"ScaleX":0.627451,"ScaleY":0.833333,"TextData":{"Alignment":1,"Color":"#ffff00","FontFamily":"Gaegu-Bold.ttf","FontSize":32,"MaxWidth":200,"OutlineColor":"#000000","OutlineOpacity":100,"OutlineSize":4,"Text":{"Text":"HEROIC","Type":0}},"Type":0,"X":326,"Y":81},{"Animations":[],"Children":[],"Conditions":[{"Code":"return $gameParty.members()[3] && $gameParty.members()[3].isStateAffected(3);","Type":9}],"CustomProperties":{},"ID":283,"Name":"Heroic Turns - Copy 3","Note":"","Opacity":1,"Rotation":0,"ScaleX":0.5,"ScaleY":0.5,"TextData":{"Alignment":1,"Color":"#ffff00","FontFamily":"Gaegu-Bold.ttf","FontSize":32,"MaxWidth":200,"OutlineColor":"#000000","OutlineOpacity":100,"OutlineSize":4,"Text":{"Code":"var actor = $gameParty.members()[3]\nvar stateId = 3; \n\nif (actor && actor.isStateAffected(stateId)) {\n    return actor.stateTurns(stateId);\n} else {\n    return \"\";\n}","Display":"(code)","Type":7}},"Type":0,"X":361,"Y":74},{"Animations":[],"Children":[],"Conditions":[{"Code":"return $gameParty.members()[3] && $gameParty.members()[3].isStateAffected(4);","Type":9}],"CustomProperties":{},"ID":267,"Name":"Frantic Check - Copy 3","Note":"","Opacity":1,"Rotation":0,"ScaleX":0.627451,"ScaleY":0.833333,"TextData":{"Alignment":1,"Color":"#ff0000","FontFamily":"Gaegu-Bold.ttf","FontSize":32,"MaxWidth":200,"OutlineColor":"#000000","OutlineOpacity":100,"OutlineSize":4,"Text":{"Text":"FRANTIC","Type":0}},"Type":0,"X":326,"Y":81},{"Animations":[],"Children":[],"Conditions":[{"Code":"return $gameParty.members()[3] && $gameParty.members()[3].isStateAffected(5);","Type":9}],"CustomProperties":{},"ID":268,"Name":"Hopeless Check - Copy 3","Note":"","Opacity":1,"Rotation":0,"ScaleX":0.627451,"ScaleY":0.833333,"TextData":{"Alignment":1,"Color":"#0223ff","FontFamily":"Gaegu-Bold.ttf","FontSize":32,"MaxWidth":200,"OutlineColor":"#000000","OutlineOpacity":100,"OutlineSize":4,"Text":{"Text":"HOPELESS","Type":0}},"Type":0,"X":326,"Y":81},{"Animations":[],"Children":[],"Conditions":[{"Code":"return $gameParty.members()[3] && $gameParty.members()[3].isStateAffected(6);","Type":9}],"CustomProperties":{},"ID":269,"Name":"Martyr Check - Copy 3","Note":"","Opacity":1,"Rotation":0,"ScaleX":0.656863,"ScaleY":0.833333,"TextData":{"Alignment":1,"Color":"#a9ac00","FontFamily":"Gaegu-Bold.ttf","FontSize":32,"MaxWidth":200,"OutlineColor":"#000000","OutlineOpacity":100,"OutlineSize":4,"Text":{"Text":"MARTYR","Type":0}},"Type":0,"X":326,"Y":81},{"Animations":[],"Children":[],"Conditions":[{"Code":"return $gameParty.members()[3] && $gameParty.members()[3].isStateAffected(7);","Type":9}],"CustomProperties":{},"ID":270,"Name":"Hysterical Check - Copy 3","Note":"","Opacity":1,"Rotation":0,"ScaleX":0.627451,"ScaleY":0.833333,"TextData":{"Alignment":1,"Color":"#ff0000","FontFamily":"Gaegu-Bold.ttf","FontSize":32,"MaxWidth":200,"OutlineColor":"#000000","OutlineOpacity":100,"OutlineSize":4,"Text":{"Text":"HYSTERICAL","Type":0}},"Type":0,"X":326,"Y":81},{"Animations":[],"Children":[],"Conditions":[{"Code":"return $gameParty.members()[3] && $gameParty.members()[3].isStateAffected(8);","Type":9}],"CustomProperties":{},"ID":271,"Name":"Despair Check - Copy 3","Note":"","Opacity":1,"Rotation":0,"ScaleX":0.637255,"ScaleY":0.833333,"TextData":{"Alignment":1,"Color":"#01138a","FontFamily":"Gaegu-Bold.ttf","FontSize":32,"MaxWidth":200,"OutlineColor":"#000000","OutlineOpacity":100,"OutlineSize":4,"Text":{"Text":"DESPAIR","Type":0}},"Type":0,"X":328,"Y":83}],"Conditions":[{"Code":"return $gameParty.members()[3] && $gameParty.members()[3].isAlive();","Type":9}],"CustomProperties":{},"Expanded":false,"GroupData":{},"ID":356,"Name":"Is Alive","Note":"","Opacity":1,"Rotation":0,"Type":6,"X":-238,"Y":78},{"Animations":[],"Children":[{"Animations":[],"CustomProperties":{},"ID":355,"Name":"Sleep - Copy 3","Note":"","Opacity":1,"Rotation":0,"ScaleX":0.628019,"ScaleY":0.792453,"TextData":{"Alignment":1,"Color":"#000000","FontFamily":"KleeOne-SemiBold.ttf","FontSize":32,"MaxWidth":200,"OutlineColor":"#bababa","OutlineOpacity":100,"OutlineSize":4,"Text":{"Text":"SLEEP","Type":0}},"Type":0,"X":327,"Y":80}],"Conditions":[{"Code":"return $gameParty.members()[3] && !$gameParty.members()[3].isAlive();","Type":9}],"CustomProperties":{},"Expanded":true,"GroupData":{},"ID":354,"Name":"Is Dead - Copy 6","Note":"","Opacity":1,"Rotation":0,"Type":6,"X":-238,"Y":78}],"CustomProperties":{},"Expanded":true,"GroupData":{},"ID":262,"Name":"State Card - Copy 3","Note":"","Opacity":1,"Rotation":0,"Type":6,"X":-81,"Y":-147},{"Animations":[],"Children":[{"Animations":[],"CustomProperties":{},"ID":273,"Name":"Container - Copy 3","Note":"","Opacity":1,"Rotation":0,"ShapeData":{"Color":"#cfcfcf","Height":60,"OutlineColor":"#000000","OutlineOpacity":100,"OutlineSize":2,"Shape":0,"Width":144},"Type":1,"X":-43,"Y":0},{"Animations":[],"CustomProperties":{},"ID":274,"Name":"Hp Icon - Copy 3","Note":"","Opacity":1,"PictureData":{"Picture":"hp-icon"},"Rotation":0,"ScaleX":0.078,"ScaleY":0.07,"Type":2,"X":-95,"Y":-14},{"Animations":[],"CustomProperties":{},"GaugeData":{"BackgroundColor":"#333333","Color1":"#f02631","Color2":"#f02631","Height":20,"Maximum":{"ActorType":false,"Index":4,"Info":8,"Type":4},"OutlineColor":"#000000","OutlineOpacity":80,"OutlineSize":2,"Smoothness":20,"SyncComponent":"","Value":{"ActorType":false,"Index":4,"Info":3,"Type":4},"Width":100},"ID":275,"Name":"Hp Gauge - Copy 3","Note":"","Opacity":1,"Rotation":0,"Type":4,"X":-28,"Y":-14},{"Animations":[],"CustomProperties":{},"ID":276,"Name":"Hp/Mhp - Copy 3","Note":"","Opacity":1,"Rotation":0,"ScaleX":0.45098,"ScaleY":0.8235290000000001,"TextData":{"Alignment":2,"Color":"#ffffff","FontFamily":"Gaegu-Bold.ttf","FontSize":30,"MaxWidth":200,"OutlineColor":"#000000","OutlineOpacity":100,"OutlineSize":4,"Text":{"Code":"const member = $gameParty.members()[3];\nif (!member) return \"\";\nreturn member.hp + \"/\" + member.mhp;","Display":"(hp/mhp)","Type":7}},"Type":0,"X":-27,"Y":-14},{"Animations":[],"CustomProperties":{},"ID":277,"Name":"Mp Icon - Copy 3","Note":"","Opacity":1,"PictureData":{"Picture":"mp-icon"},"Rotation":0,"ScaleX":0.278,"ScaleY":0.22,"Type":2,"X":-95,"Y":13},{"Animations":[],"Children":[],"CustomProperties":{},"GaugeData":{"BackgroundColor":"#333333","Color1":"#11a7df","Color2":"#11a7df","Height":20,"Maximum":{"ActorType":false,"Index":4,"Info":9,"Type":4},"OutlineColor":"#000000","OutlineOpacity":80,"OutlineSize":2,"Smoothness":20,"SyncComponent":"","Value":{"ActorType":false,"Index":4,"Info":4,"Type":4},"Width":100},"ID":278,"Name":"Mana Gauge - Copy 3","Note":"","Opacity":1,"Rotation":0,"Type":4,"X":-28,"Y":13},{"Animations":[],"Children":[],"CustomProperties":{},"ID":279,"Name":"Mp/Mmp - Copy 3","Note":"","Opacity":1,"Rotation":0,"ScaleX":0.45,"ScaleY":0.823,"TextData":{"Alignment":2,"Color":"#ffffff","FontFamily":"Gaegu-Bold.ttf","FontSize":30,"MaxWidth":200,"OutlineColor":"#000000","OutlineOpacity":100,"OutlineSize":4,"Text":{"Code":"const member = $gameParty.members()[3];\nif (!member) return \"\";\nreturn member.mp + \"/\" + member.mmp;","Display":"(mp/mmp)","Type":7}},"Type":0,"X":-27,"Y":13}],"CustomProperties":{},"Expanded":true,"GroupData":{},"ID":272,"Name":"Status Card - Copy 3","Note":"","Opacity":1,"Rotation":0,"Type":6,"X":50,"Y":198}],"Conditions":[{"Code":"return $gameParty.members().length >= 4;","Type":9}],"CustomProperties":{},"Expanded":true,"GroupData":{},"ID":257,"Name":"Party 4","Note":"","Opacity":1,"Rotation":0,"Type":6,"X":727,"Y":379},{"Animations":[],"Children":[{"Animations":[],"CustomProperties":{},"ID":292,"Name":"OuContainer","Note":"","Opacity":1,"Rotation":0,"ShapeData":{"Color":"#cac9ca","Height":56,"OutlineColor":"#000000","OutlineOpacity":100,"OutlineSize":2,"Shape":0,"Width":166},"Type":1,"X":0,"Y":-153},{"Animations":[],"CustomProperties":{},"ID":294,"Name":"InContainer","Note":"","Opacity":1,"Rotation":0,"ShapeData":{"Color":"#ffffff","Height":30,"OutlineColor":"#000000","OutlineOpacity":100,"OutlineSize":2,"Shape":0,"Width":152},"Type":1,"X":0,"Y":-171},{"Animations":[],"Children":[],"Conditions":[{"Code":"return $gameTroop.members()[0] && !$gameTroop.members()[0].isStateAffected(3) && !$gameTroop.members()[0].isStateAffected(4) && !$gameTroop.members()[0].isStateAffected(5);","Type":9}],"CustomProperties":{},"ID":299,"Name":"Neutral State Name","Note":"","Opacity":1,"Rotation":0,"ScaleX":1,"ScaleY":1,"TextData":{"Alignment":1,"Color":"#ffffff","FontFamily":"Cinzel-Bold.ttf","FontSize":20,"MaxWidth":200,"OutlineColor":"#000000","OutlineOpacity":100,"OutlineSize":2,"Text":{"Code":"return $gameTroop.members()[0].name();","Display":"(code)","Type":7}},"Type":0,"X":0,"Y":-171},{"Animations":[],"Children":[],"Conditions":[{"Code":"return $gameTroop.members()[0] && $gameTroop.members()[0].isStateAffected(3);","Type":9}],"CustomProperties":{},"ID":300,"Name":"Heroic State Name","Note":"","Opacity":1,"Rotation":0,"ScaleX":1,"ScaleY":1,"TextData":{"Alignment":1,"Color":"#ffd700","FontFamily":"Cinzel-Bold.ttf","FontSize":20,"MaxWidth":200,"OutlineColor":"#000000","OutlineOpacity":100,"OutlineSize":4,"Text":{"Code":"return $gameTroop.members()[0].name().toUpperCase();","Display":"(code)","Type":7}},"Type":0,"X":0,"Y":-171},{"Animations":[],"Children":[],"Conditions":[{"Code":"return $gameTroop.members()[0] && $gameTroop.members()[0].isStateAffected(4);","Type":9}],"CustomProperties":{},"ID":297,"Name":"Frantic State Name","Note":"","Opacity":1,"Rotation":0,"ScaleX":1,"ScaleY":1,"TextData":{"Alignment":1,"Color":"#ff0000","FontFamily":"Creepster-Regular.ttf","FontSize":20,"MaxWidth":200,"OutlineColor":"#000000","OutlineOpacity":100,"OutlineSize":4,"Text":{"Code":"return $gameTroop.members()[0].name().toUpperCase().split('').join(' ');","Display":"(code)","Type":7}},"Type":0,"X":0,"Y":-171},{"Animations":[],"Children":[],"Conditions":[{"Code":"return $gameTroop.members()[0] && $gameTroop.members()[0].isStateAffected(5);","Type":9}],"CustomProperties":{},"ID":298,"Name":"Hopeless State Name","Note":"","Opacity":1,"Rotation":0,"ScaleX":1,"ScaleY":1,"TextData":{"Alignment":1,"Color":"#11a7df","FontFamily":"ShadowsIntoLight-Regular.ttf","FontSize":22,"MaxWidth":200,"OutlineColor":"#000000","OutlineOpacity":100,"OutlineSize":4,"Text":{"Code":"return $gameTroop.members()[0].name().toLowerCase();","Display":"(code)","Type":7}},"Type":0,"X":0,"Y":-171},{"Animations":[],"Children":[],"Conditions":[{"Code":"return $gameParty.inBattle() && $gameSwitches.value(101);","Type":9}],"CustomProperties":{},"ID":295,"Name":"Breakthrough Icon","Note":"","Opacity":1,"PictureData":{"Picture":"hp-icon"},"Rotation":0,"ScaleX":0.059000000000000004,"ScaleY":0.05,"Type":2,"X":-66,"Y":-140},{"Animations":[],"Conditions":[{"Code":"return $gameParty.inBattle() && $gameSwitches.value(101);","Type":9}],"CustomProperties":{},"GaugeData":{"BackgroundColor":"#333333","Color1":"#f02631","Color2":"#f02631","Height":14,"Maximum":{"Code":"return $gameTroop.members()[0] ? $gameTroop.members()[0].mhp : 1;","Display":"(code)","Type":7},"OutlineColor":"#000000","OutlineOpacity":100,"OutlineSize":2,"Smoothness":20,"SyncComponent":"","Value":{"Code":"return $gameTroop.members()[0] ? $gameTroop.members()[0].hp : 0;","Display":"(code)","Type":7},"Width":128},"ID":289,"Name":"Breakthrough Gauge","Note":"","Opacity":1,"Rotation":0,"Type":4,"X":12,"Y":-140},{"Animations":[],"Conditions":[{"Code":"return $gameParty.inBattle() && $gameSwitches.value(102);","Type":9}],"CustomProperties":{},"ID":296,"Name":"Escape Icon","Note":"","Opacity":1,"PictureData":{"Picture":"escape"},"Rotation":0,"ScaleX":0.075,"ScaleY":0.075,"Type":2,"X":-66,"Y":-140},{"Animations":[],"Children":[],"Conditions":[{"Code":"return $gameParty.inBattle() && $gameSwitches.value(102);","Type":9}],"CustomProperties":{},"GaugeData":{"BackgroundColor":"#333333","Color1":"#ff5f2f","Color2":"#ff5f2f","Height":14,"Maximum":{"Code":"return $gameTroop.members()[0] ? $gameTroop.members()[0].mhp : 1;","Display":"(code)","Type":7},"OutlineColor":"#000000","OutlineOpacity":100,"OutlineSize":2,"Smoothness":20,"SyncComponent":"","Value":{"Code":"return $gameTroop.members()[0] ? ($gameTroop.members()[0].mhp - $gameTroop.members()[0].hp) : 0;","Display":"(code)","Type":7},"Width":128},"ID":290,"Name":"Escape Gauge","Note":"","Opacity":1,"Rotation":0,"Type":4,"X":12,"Y":-140}],"Conditions":[{"Code":"return $gameParty.inBattle() && $gameTroop.members()[0] && $gameTroop.members()[0].isSelected();","Type":9}],"CustomProperties":{},"Expanded":false,"GroupData":{},"ID":291,"Name":"Enemy","Note":"","Opacity":1,"Rotation":0,"Type":6,"X":408,"Y":523}]}],"Map":0}